MANIFEST.in
README.md
setup.py
dbt/adapters/datafusion/__init__.py
dbt/adapters/datafusion/__version__.py
dbt/adapters/datafusion/connections.py
dbt/adapters/datafusion/db.py
dbt/adapters/datafusion/impl.py
dbt/adapters/datafusion/relation.py
dbt/include/datafusion/__init__.py
dbt/include/datafusion/dbt_project.yml
dbt/include/datafusion/profile_template.yml
dbt/include/datafusion/macros/adapters.sql
dbt/include/datafusion/macros/catalog.sql
dbt/include/datafusion/macros/materializations/table.sql
dbt_datafusion.egg-info/PKG-INFO
dbt_datafusion.egg-info/SOURCES.txt
dbt_datafusion.egg-info/dependency_links.txt
dbt_datafusion.egg-info/requires.txt
dbt_datafusion.egg-info/top_level.txt